{
  "generator-jhipster": {
    "applicationType": "monolith",
    "authenticationType": "jwt",
    "baseName": "jhipsterVueApplication",
    "blueprints": [],
    "buildTool": "maven",
    "cacheProvider": "ehcache",
    "clientFramework": "vue",
    "clientPackageManager": "npm",
    "creationTimestamp": 1728223038542,
    "databaseType": "sql",
    "devDatabaseType": "h2Disk",
    "devServerPort": 9060,
    "enableHibernateCache": true,
    "enableSwaggerCodegen": "true",
    "enableTranslation": true,
    "entities": [],
    "gitCompany": "",
    "jhiPrefix": "jhi",
    "jhipsterVersion": "8.7.1",
    "jwtSecretKey": "M2U2N2Q5ZWJmOTE2YWViZTg1MTMzNTQ2M2RiYWU3NzRhNzgwMzM5NmZhMWRmN2JlZDQ4M2NlNDI5ZGEwNDBhNThjYWYzOWJkMTg2NDYyMzI0MmZjYzlkZjZmYWE1NWU2ZDZjMGZhNzUyMDU1ZTUyY2ZiYmFmY2VjODY2MTczMjc=",
    "languages": ["en", "de"],
    "messageBroker": false,
    "nativeLanguage": "en",
    "packageFolder": "de/intagau/myvueapp",
    "packageName": "de.intagau.myvueapp",
    "prodDatabaseType": "postgresql",
    "searchEngine": false,
    "serverPort": 8080,
    "serviceDiscoveryType": false,
    "testFrameworks": [],
    "useSass": true,
    "websocket": false,
    "withAdminUi": true
  },
  "git-company": "th-gauweiler",
  "git-provider": "GitHub",
  "repository-name": "jhipster-vue-application"
}
